{
  "name": "Forest Park Apartments",
  "address": "2605 W Maplewood Ave, Bellingham, WA 98225",
  "company_type": "property",
  "review_count": 9,
  "avg_review": 3.0,
  "reviews": [
    {
      "author": "Halfkin Rainbolt",
      "rating": 4.0,
      "review": "I moved in,  early 2022, shortly after the business was bought by a new company. I have had a wonderful experience with the management and no problems to speak of. The maintenance is good, prompt and friendly. I recommend this to others. ",
      "ownerResponse": []
    },
    {
      "author": "Lynda Galbraith",
      "rating": 4.0,
      "review": "We delivered to a nice lady here. The one bedroom was nice size. Nice inside. Seems quiet",
      "ownerResponse": []
    },
    {
      "author": "Mesake Tudrau",
      "rating": 1.0,
      "review": "It's  an old apartment with high rent. I suppose to get a refund back but it seems like they don't bother. A stubborn officer with not very friendly approach in the ofgice.",
      "ownerResponse": []
    },
    {
      "author": "Andrew Davis",
      "rating": 5.0,
      "review": "Recently tenents have been complaining about high rent increassess at Forest park apartments.  It appears to me this is primarily the result of the high inflation, nationally.  SUHRCO is the new company managing Forest Park apartments.  To ",
      "ownerResponse": []
    },
    {
      "author": "Tasha Beckham",
      "rating": 1.0,
      "review": "We needed a new washer and they brought over a used dirty one and it started spitting all this dirty and stuff but now my kids blankets smell so bad and have stuff all over it smh",
      "ownerResponse": []
    },
    {
      "author": "make America great again",
      "rating": 1.0,
      "review": "They fail to tell you that a methadone clinic is across the street.",
      "ownerResponse": []
    },
    {
      "author": "Lisa's World",
      "rating": 5.0,
      "review": "",
      "ownerResponse": []
    },
    {
      "author": "M B",
      "rating": 1.0,
      "review": "",
      "ownerResponse": []
    },
    {
      "author": "Milangela Diaz",
      "rating": 5.0,
      "review": "",
      "ownerResponse": []
    }
  ],
  "adjusted_review_count": 6,
  "adjusted_review_average": 2.7
}