{
  "name": "Newport Apartments Bellingham",
  "address": "602 32nd St, Bellingham, WA 98225",
  "company_type": "Apartment building",
  "review_count": 2,
  "avg_review": 2.0,
  "reviews": [
    {
      "author": "Cecilia Smith",
      "rating": 3.0,
      "review": "These apartments get the job done, and while you aren't getting high quality, the prices are good for this area. When I moved into my unit last year, my unit contained fleas, which the property management company appeared to have known ",
      "ownerResponse": []
    },
    {
      "author": "Olivia Stark",
      "rating": 1.0,
      "review": "I love the community and area. This complex has ruined the experience Bellingham had to offer due to the unprofessional staff who chose to not abide by the RCW codes they so rudely told me to \"look up.\" On one hand they're billing me after ",
      "ownerResponse": []
    }
  ],
  "adjusted_review_count": 2,
  "adjusted_review_average": 2.0
}